apihelper/__init__.py
apihelper/manage.py
apihelper/settings.py
apihelper/api/BaseApi.py
apihelper/api/HelloworldApi.py
apihelper/api/__init__.py
apihelper/database/__init__.py
apihelper/database/models.py
apihelper/handlers/BaseHandler.py
apihelper/handlers/HelloWorldHandler.py
apihelper/handlers/__init__.py
apihelper/response/BaseResponse.py
apihelper/response/__init__.py
apihelper/security/__init__.py
apihelper/security/crypo.py
apihelper/security/hasher.py
apihelper/thirdparty/__init__.py
apihelper/thirdparty/demos/CertService.py
apihelper/thirdparty/demos/CurrentTempService.py
apihelper/thirdparty/demos/DemoServices.py
apihelper/thirdparty/demos/DemoServices2.py
apihelper/thirdparty/demos/DemoServicesHostname.py
apihelper/thirdparty/demos/HelloWorldAsyncService.py
apihelper/thirdparty/demos/HelloWorldService.py
apihelper/thirdparty/demos/HelloWorldService2.py
apihelper/thirdparty/demos/MathService.py
apihelper/thirdparty/demos/ProductListService.py
apihelper/thirdparty/demos/ProductListService2.py
apihelper/thirdparty/demos/ProductService.py
apihelper/thirdparty/demos/RegisterService.py
apihelper/thirdparty/demos/RepositoryService.py
apihelper/thirdparty/demos/UserRolesService.py
apihelper/thirdparty/demos/__init__.py
apihelper/thirdparty/tornadows/__init__.py
apihelper/thirdparty/tornadows/complextypes.py
apihelper/thirdparty/tornadows/soap.py
apihelper/thirdparty/tornadows/soaphandler.py
apihelper/thirdparty/tornadows/webservices.py
apihelper/thirdparty/tornadows/wsdl.py
apihelper/thirdparty/tornadows/xmltypes.py
snowland_apihelper-0.0.3.dist-info/DESCRIPTION.rst
snowland_apihelper-0.0.3.dist-info/METADATA
snowland_apihelper-0.0.3.dist-info/RECORD
snowland_apihelper-0.0.3.dist-info/WHEEL
snowland_apihelper-0.0.3.dist-info/metadata.json
snowland_apihelper-0.0.3.dist-info/top_level.txt
